bryt_aws_sam_template/__init__.py
bryt_aws_sam_template/cli.py
bryt_aws_sam_template/__pycache__/__init__.cpython-311.pyc
bryt_aws_sam_template/__pycache__/cli.cpython-311.pyc
bryt_aws_sam_template/runner/TemplateRunner.py
bryt_aws_sam_template/runner/__init__.py
bryt_aws_sam_template/runner/samconfig.toml
bryt_aws_sam_template/runner/DevOpsRunner/__init__.py
bryt_aws_sam_template/runner/DevOpsRunner/template.yaml
bryt_aws_sam_template/runner/DevOpsRunner/__pycache__/__init__.cpython-311.pyc
bryt_aws_sam_template/runner/DevOpsRunner/__pycache__/dev_ops_runner.cpython-311.pyc
bryt_aws_sam_template/runner/HttpWebsiteRunner/__init__.py
bryt_aws_sam_template/runner/HttpWebsiteRunner/template.yaml
bryt_aws_sam_template/runner/HttpWebsiteRunner/__pycache__/__init__.cpython-311.pyc
bryt_aws_sam_template/runner/HttpWebsiteRunner/__pycache__/http_website_runner.cpython-311.pyc
bryt_aws_sam_template/runner/HttpsWebsiteRunner/__init__.py
bryt_aws_sam_template/runner/HttpsWebsiteRunner/acm-certificate.yaml
bryt_aws_sam_template/runner/HttpsWebsiteRunner/cloudfront-site.yaml
bryt_aws_sam_template/runner/HttpsWebsiteRunner/s3-bucket.yaml
bryt_aws_sam_template/runner/HttpsWebsiteRunner/template.yaml
bryt_aws_sam_template/runner/HttpsWebsiteRunner/__pycache__/__init__.cpython-311.pyc
bryt_aws_sam_template/runner/HttpsWebsiteRunner/__pycache__/https_website_runner.cpython-311.pyc
bryt_aws_sam_template/runner/UserPoolRunner/__init__.py
bryt_aws_sam_template/runner/UserPoolRunner/index.yaml
bryt_aws_sam_template/runner/UserPoolRunner/template.yaml
bryt_aws_sam_template/runner/UserPoolRunner/test-api.yaml
bryt_aws_sam_template/runner/UserPoolRunner/user-pool.yaml
bryt_aws_sam_template/runner/UserPoolRunner/__pycache__/__init__.cpython-311.pyc
bryt_aws_sam_template/runner/UserPoolRunner/__pycache__/user_pool_runner.cpython-311.pyc
bryt_aws_sam_template/runner/UserPoolRunner/hello_world/__init__.py
bryt_aws_sam_template/runner/UserPoolRunner/hello_world/app.py
bryt_aws_sam_template-1.0.4.dist-info/LICENSE
bryt_aws_sam_template-1.0.4.dist-info/METADATA
bryt_aws_sam_template-1.0.4.dist-info/WHEEL
bryt_aws_sam_template-1.0.4.dist-info/entry_points.txt
bryt_aws_sam_template-1.0.4.dist-info/top_level.txt
bryt_aws_sam_template-1.0.4.dist-info/RECORD
