Metadata-Version: 2.1
Name: bryt-aws-sam-template
Version: 1.0.4
Summary: AWS SAM Template
Author-email: Bryt <bryt.xin.li@gmail.com>
Project-URL: Homepage, https://github.com/xin-at-marathon/makefile
Project-URL: Issues, https://github.com/xin-at-marathon/makefile/issues
Classifier: Programming Language :: Python :: 3
Classifier: License :: OSI Approved :: MIT License
Classifier: Operating System :: OS Independent
Requires-Python: >=3.6
License-File: LICENSE
Requires-Dist: python-dotenv
Requires-Dist: termcolor
Requires-Dist: boto3
